{
  "openapi": "3.0.4",
  "info": {
    "title": "Spill The Beanz Coffee Shop API",
    "version": "1.0"
  },
  "paths": {
    "/api/Customers": {
      "get": {
        "tags": [
          "Customers"
        ],
        "responses": {
          "200": {
            "description": "OK",
            "content": {
              "text/plain": {
                "schema": {
                  "type": "array",
                  "items": {
                    "$ref": "#/components/schemas/CustomerDTOOrderGET"
                  }
                }
              },
              "application/json": {
                "schema": {
                  "type": "array",
                  "items": {
                    "$ref": "#/components/schemas/CustomerDTOOrderGET"
                  }
                }
              },
              "text/json": {
                "schema": {
                  "type": "array",
                  "items": {
                    "$ref": "#/components/schemas/CustomerDTOOrderGET"
                  }
                }
              }
            }
          }
        }
      },
      "post": {
        "tags": [
          "Customers"
        ],
        "requestBody": {
          "content": {
            "application/json-patch+json": {
              "schema": {
                "$ref": "#/components/schemas/CustomerDTOP"
              }
            },
            "application/json": {
              "schema": {
                "$ref": "#/components/schemas/CustomerDTOP"
              }
            },
            "text/json": {
              "schema": {
                "$ref": "#/components/schemas/CustomerDTOP"
              }
            },
            "application/*+json": {
              "schema": {
                "$ref": "#/components/schemas/CustomerDTOP"
              }
            }
          }
        },
        "responses": {
          "200": {
            "description": "OK",
            "content": {
              "text/plain": {
                "schema": {
                  "$ref": "#/components/schemas/Customers"
                }
              },
              "application/json": {
                "schema": {
                  "$ref": "#/components/schemas/Customers"
                }
              },
              "text/json": {
                "schema": {
                  "$ref": "#/components/schemas/Customers"
                }
              }
            }
          }
        }
      }
    },
    "/api/Customers/{id}": {
      "get": {
        "tags": [
          "Customers"
        ],
        "parameters": [
          {
            "name": "id",
            "in": "path",
            "required": true,
            "schema": {
              "type": "integer",
              "format": "int32"
            }
          }
        ],
        "responses": {
          "200": {
            "description": "OK",
            "content": {
              "text/plain": {
                "schema": {
                  "$ref": "#/components/schemas/CustomerDTOGet"
                }
              },
              "application/json": {
                "schema": {
                  "$ref": "#/components/schemas/CustomerDTOGet"
                }
              },
              "text/json": {
                "schema": {
                  "$ref": "#/components/schemas/CustomerDTOGet"
                }
              }
            }
          }
        }
      },
      "put": {
        "tags": [
          "Customers"
        ],
        "parameters": [
          {
            "name": "id",
            "in": "path",
            "required": true,
            "schema": {
              "type": "integer",
              "format": "int32"
            }
          }
        ],
        "requestBody": {
          "content": {
            "application/json-patch+json": {
              "schema": {
                "$ref": "#/components/schemas/CustomerDTOP"
              }
            },
            "application/json": {
              "schema": {
                "$ref": "#/components/schemas/CustomerDTOP"
              }
            },
            "text/json": {
              "schema": {
                "$ref": "#/components/schemas/CustomerDTOP"
              }
            },
            "application/*+json": {
              "schema": {
                "$ref": "#/components/schemas/CustomerDTOP"
              }
            }
          }
        },
        "responses": {
          "200": {
            "description": "OK"
          }
        }
      },
      "patch": {
        "tags": [
          "Customers"
        ],
        "parameters": [
          {
            "name": "id",
            "in": "path",
            "required": true,
            "schema": {
              "type": "integer",
              "format": "int32"
            }
          }
        ],
        "requestBody": {
          "content": {
            "application/json-patch+json": {
              "schema": {
                "type": "array",
                "items": {
                  "$ref": "#/components/schemas/Operation"
                }
              }
            },
            "application/json": {
              "schema": {
                "type": "array",
                "items": {
                  "$ref": "#/components/schemas/Operation"
                }
              }
            },
            "text/json": {
              "schema": {
                "type": "array",
                "items": {
                  "$ref": "#/components/schemas/Operation"
                }
              }
            },
            "application/*+json": {
              "schema": {
                "type": "array",
                "items": {
                  "$ref": "#/components/schemas/Operation"
                }
              }
            }
          }
        },
        "responses": {
          "200": {
            "description": "OK"
          }
        }
      },
      "delete": {
        "tags": [
          "Customers"
        ],
        "parameters": [
          {
            "name": "id",
            "in": "path",
            "required": true,
            "schema": {
              "type": "integer",
              "format": "int32"
            }
          }
        ],
        "responses": {
          "200": {
            "description": "OK"
          }
        }
      }
    },
    "/api/ItemVariants": {
      "get": {
        "tags": [
          "ItemVariants"
        ],
        "responses": {
          "200": {
            "description": "OK",
            "content": {
              "text/plain": {
                "schema": {
                  "type": "array",
                  "items": {
                    "$ref": "#/components/schemas/ItemVariants"
                  }
                }
              },
              "application/json": {
                "schema": {
                  "type": "array",
                  "items": {
                    "$ref": "#/components/schemas/ItemVariants"
                  }
                }
              },
              "text/json": {
                "schema": {
                  "type": "array",
                  "items": {
                    "$ref": "#/components/schemas/ItemVariants"
                  }
                }
              }
            }
          }
        }
      },
      "post": {
        "tags": [
          "ItemVariants"
        ],
        "requestBody": {
          "content": {
            "application/json-patch+json": {
              "schema": {
                "$ref": "#/components/schemas/ItemVariants"
              }
            },
            "application/json": {
              "schema": {
                "$ref": "#/components/schemas/ItemVariants"
              }
            },
            "text/json": {
              "schema": {
                "$ref": "#/components/schemas/ItemVariants"
              }
            },
            "application/*+json": {
              "schema": {
                "$ref": "#/components/schemas/ItemVariants"
              }
            }
          }
        },
        "responses": {
          "200": {
            "description": "OK",
            "content": {
              "text/plain": {
                "schema": {
                  "$ref": "#/components/schemas/ItemVariants"
                }
              },
              "application/json": {
                "schema": {
                  "$ref": "#/components/schemas/ItemVariants"
                }
              },
              "text/json": {
                "schema": {
                  "$ref": "#/components/schemas/ItemVariants"
                }
              }
            }
          }
        }
      }
    },
    "/api/ItemVariants/{id}": {
      "get": {
        "tags": [
          "ItemVariants"
        ],
        "parameters": [
          {
            "name": "id",
            "in": "path",
            "required": true,
            "schema": {
              "type": "integer",
              "format": "int32"
            }
          }
        ],
        "responses": {
          "200": {
            "description": "OK",
            "content": {
              "text/plain": {
                "schema": {
                  "$ref": "#/components/schemas/ItemVariants"
                }
              },
              "application/json": {
                "schema": {
                  "$ref": "#/components/schemas/ItemVariants"
                }
              },
              "text/json": {
                "schema": {
                  "$ref": "#/components/schemas/ItemVariants"
                }
              }
            }
          }
        }
      },
      "put": {
        "tags": [
          "ItemVariants"
        ],
        "parameters": [
          {
            "name": "id",
            "in": "path",
            "required": true,
            "schema": {
              "type": "integer",
              "format": "int32"
            }
          }
        ],
        "requestBody": {
          "content": {
            "application/json-patch+json": {
              "schema": {
                "$ref": "#/components/schemas/ItemVariants"
              }
            },
            "application/json": {
              "schema": {
                "$ref": "#/components/schemas/ItemVariants"
              }
            },
            "text/json": {
              "schema": {
                "$ref": "#/components/schemas/ItemVariants"
              }
            },
            "application/*+json": {
              "schema": {
                "$ref": "#/components/schemas/ItemVariants"
              }
            }
          }
        },
        "responses": {
          "200": {
            "description": "OK"
          }
        }
      },
      "delete": {
        "tags": [
          "ItemVariants"
        ],
        "parameters": [
          {
            "name": "id",
            "in": "path",
            "required": true,
            "schema": {
              "type": "integer",
              "format": "int32"
            }
          }
        ],
        "responses": {
          "200": {
            "description": "OK"
          }
        }
      }
    },
    "/api/Orders": {
      "get": {
        "tags": [
          "Orders"
        ],
        "responses": {
          "200": {
            "description": "OK",
            "content": {
              "text/plain": {
                "schema": {
                  "type": "array",
                  "items": {
                    "$ref": "#/components/schemas/Orders"
                  }
                }
              },
              "application/json": {
                "schema": {
                  "type": "array",
                  "items": {
                    "$ref": "#/components/schemas/Orders"
                  }
                }
              },
              "text/json": {
                "schema": {
                  "type": "array",
                  "items": {
                    "$ref": "#/components/schemas/Orders"
                  }
                }
              }
            }
          }
        }
      },
      "post": {
        "tags": [
          "Orders"
        ],
        "requestBody": {
          "content": {
            "application/json-patch+json": {
              "schema": {
                "$ref": "#/components/schemas/Orders"
              }
            },
            "application/json": {
              "schema": {
                "$ref": "#/components/schemas/Orders"
              }
            },
            "text/json": {
              "schema": {
                "$ref": "#/components/schemas/Orders"
              }
            },
            "application/*+json": {
              "schema": {
                "$ref": "#/components/schemas/Orders"
              }
            }
          }
        },
        "responses": {
          "200": {
            "description": "OK",
            "content": {
              "text/plain": {
                "schema": {
                  "$ref": "#/components/schemas/Orders"
                }
              },
              "application/json": {
                "schema": {
                  "$ref": "#/components/schemas/Orders"
                }
              },
              "text/json": {
                "schema": {
                  "$ref": "#/components/schemas/Orders"
                }
              }
            }
          }
        }
      }
    },
    "/api/Orders/{id}": {
      "get": {
        "tags": [
          "Orders"
        ],
        "parameters": [
          {
            "name": "id",
            "in": "path",
            "required": true,
            "schema": {
              "type": "integer",
              "format": "int32"
            }
          }
        ],
        "responses": {
          "200": {
            "description": "OK",
            "content": {
              "text/plain": {
                "schema": {
                  "$ref": "#/components/schemas/Orders"
                }
              },
              "application/json": {
                "schema": {
                  "$ref": "#/components/schemas/Orders"
                }
              },
              "text/json": {
                "schema": {
                  "$ref": "#/components/schemas/Orders"
                }
              }
            }
          }
        }
      },
      "put": {
        "tags": [
          "Orders"
        ],
        "parameters": [
          {
            "name": "id",
            "in": "path",
            "required": true,
            "schema": {
              "type": "integer",
              "format": "int32"
            }
          }
        ],
        "requestBody": {
          "content": {
            "application/json-patch+json": {
              "schema": {
                "$ref": "#/components/schemas/Orders"
              }
            },
            "application/json": {
              "schema": {
                "$ref": "#/components/schemas/Orders"
              }
            },
            "text/json": {
              "schema": {
                "$ref": "#/components/schemas/Orders"
              }
            },
            "application/*+json": {
              "schema": {
                "$ref": "#/components/schemas/Orders"
              }
            }
          }
        },
        "responses": {
          "200": {
            "description": "OK"
          }
        }
      },
      "delete": {
        "tags": [
          "Orders"
        ],
        "parameters": [
          {
            "name": "id",
            "in": "path",
            "required": true,
            "schema": {
              "type": "integer",
              "format": "int32"
            }
          }
        ],
        "responses": {
          "200": {
            "description": "OK"
          }
        }
      }
    },
    "/api/TableReservations": {
      "get": {
        "tags": [
          "TableReservations"
        ],
        "responses": {
          "200": {
            "description": "OK",
            "content": {
              "text/plain": {
                "schema": {
                  "type": "array",
                  "items": {
                    "$ref": "#/components/schemas/CustomerDTORes"
                  }
                }
              },
              "application/json": {
                "schema": {
                  "type": "array",
                  "items": {
                    "$ref": "#/components/schemas/CustomerDTORes"
                  }
                }
              },
              "text/json": {
                "schema": {
                  "type": "array",
                  "items": {
                    "$ref": "#/components/schemas/CustomerDTORes"
                  }
                }
              }
            }
          }
        }
      },
      "post": {
        "tags": [
          "TableReservations"
        ],
        "requestBody": {
          "content": {
            "application/json-patch+json": {
              "schema": {
                "$ref": "#/components/schemas/TableReservations"
              }
            },
            "application/json": {
              "schema": {
                "$ref": "#/components/schemas/TableReservations"
              }
            },
            "text/json": {
              "schema": {
                "$ref": "#/components/schemas/TableReservations"
              }
            },
            "application/*+json": {
              "schema": {
                "$ref": "#/components/schemas/TableReservations"
              }
            }
          }
        },
        "responses": {
          "200": {
            "description": "OK",
            "content": {
              "text/plain": {
                "schema": {
                  "$ref": "#/components/schemas/TableReservations"
                }
              },
              "application/json": {
                "schema": {
                  "$ref": "#/components/schemas/TableReservations"
                }
              },
              "text/json": {
                "schema": {
                  "$ref": "#/components/schemas/TableReservations"
                }
              }
            }
          }
        }
      }
    },
    "/api/TableReservations/{id}": {
      "get": {
        "tags": [
          "TableReservations"
        ],
        "parameters": [
          {
            "name": "id",
            "in": "path",
            "required": true,
            "schema": {
              "type": "integer",
              "format": "int32"
            }
          }
        ],
        "responses": {
          "200": {
            "description": "OK",
            "content": {
              "text/plain": {
                "schema": {
                  "$ref": "#/components/schemas/TableReservations"
                }
              },
              "application/json": {
                "schema": {
                  "$ref": "#/components/schemas/TableReservations"
                }
              },
              "text/json": {
                "schema": {
                  "$ref": "#/components/schemas/TableReservations"
                }
              }
            }
          }
        }
      },
      "put": {
        "tags": [
          "TableReservations"
        ],
        "parameters": [
          {
            "name": "id",
            "in": "path",
            "required": true,
            "schema": {
              "type": "integer",
              "format": "int32"
            }
          }
        ],
        "requestBody": {
          "content": {
            "application/json-patch+json": {
              "schema": {
                "$ref": "#/components/schemas/TableReservations"
              }
            },
            "application/json": {
              "schema": {
                "$ref": "#/components/schemas/TableReservations"
              }
            },
            "text/json": {
              "schema": {
                "$ref": "#/components/schemas/TableReservations"
              }
            },
            "application/*+json": {
              "schema": {
                "$ref": "#/components/schemas/TableReservations"
              }
            }
          }
        },
        "responses": {
          "200": {
            "description": "OK"
          }
        }
      },
      "patch": {
        "tags": [
          "TableReservations"
        ],
        "parameters": [
          {
            "name": "id",
            "in": "path",
            "required": true,
            "schema": {
              "type": "integer",
              "format": "int32"
            }
          }
        ],
        "requestBody": {
          "content": {
            "application/json-patch+json": {
              "schema": {
                "type": "array",
                "items": {
                  "$ref": "#/components/schemas/Operation"
                }
              }
            },
            "application/json": {
              "schema": {
                "type": "array",
                "items": {
                  "$ref": "#/components/schemas/Operation"
                }
              }
            },
            "text/json": {
              "schema": {
                "type": "array",
                "items": {
                  "$ref": "#/components/schemas/Operation"
                }
              }
            },
            "application/*+json": {
              "schema": {
                "type": "array",
                "items": {
                  "$ref": "#/components/schemas/Operation"
                }
              }
            }
          }
        },
        "responses": {
          "200": {
            "description": "OK",
            "content": {
              "text/plain": {
                "schema": {
                  "$ref": "#/components/schemas/TableReservations"
                }
              },
              "application/json": {
                "schema": {
                  "$ref": "#/components/schemas/TableReservations"
                }
              },
              "text/json": {
                "schema": {
                  "$ref": "#/components/schemas/TableReservations"
                }
              }
            }
          }
        }
      },
      "delete": {
        "tags": [
          "TableReservations"
        ],
        "parameters": [
          {
            "name": "id",
            "in": "path",
            "required": true,
            "schema": {
              "type": "integer",
              "format": "int32"
            }
          }
        ],
        "responses": {
          "200": {
            "description": "OK"
          }
        }
      }
    }
  },
  "components": {
    "schemas": {
      "Admins": {
        "type": "object",
        "properties": {
          "adminId": {
            "type": "integer",
            "format": "int32"
          },
          "adminName": {
            "type": "string",
            "nullable": true
          },
          "adminEmailAddress": {
            "type": "string",
            "nullable": true
          },
          "adminPasswordHash": {
            "type": "string",
            "nullable": true
          },
          "profileCreatedAt": {
            "type": "string",
            "format": "date-time"
          },
          "lastVogin": {
            "type": "string",
            "format": "date-time"
          },
          "promotions": {
            "type": "array",
            "items": {
              "$ref": "#/components/schemas/Promotions"
            },
            "nullable": true
          }
        },
        "additionalProperties": false
      },
      "CustomerDTOGet": {
        "type": "object",
        "properties": {
          "customerName": {
            "type": "string",
            "nullable": true
          },
          "email": {
            "type": "string",
            "nullable": true
          },
          "phoneNumber": {
            "type": "string",
            "nullable": true
          },
          "address": {
            "type": "string",
            "nullable": true
          },
          "orders": {
            "type": "array",
            "items": {
              "$ref": "#/components/schemas/OrderDto"
            },
            "nullable": true
          }
        },
        "additionalProperties": false
      },
      "CustomerDTOOrderGET": {
        "type": "object",
        "properties": {
          "customerName": {
            "type": "string",
            "nullable": true
          },
          "email": {
            "type": "string",
            "nullable": true
          },
          "phoneNumber": {
            "type": "string",
            "nullable": true
          },
          "address": {
            "type": "string",
            "nullable": true
          },
          "orders": {
            "type": "array",
            "items": {
              "$ref": "#/components/schemas/OrderDto"
            },
            "nullable": true
          }
        },
        "additionalProperties": false
      },
      "CustomerDTOP": {
        "type": "object",
        "properties": {
          "customerID": {
            "type": "integer",
            "format": "int32"
          },
          "customerName": {
            "type": "string",
            "nullable": true
          },
          "email": {
            "type": "string",
            "nullable": true
          },
          "phoneNumber": {
            "type": "string",
            "nullable": true
          },
          "address": {
            "type": "string",
            "nullable": true
          },
          "passwordHash": {
            "type": "string",
            "nullable": true
          }
        },
        "additionalProperties": false
      },
      "CustomerDTORes": {
        "type": "object",
        "properties": {
          "customerName": {
            "type": "string",
            "nullable": true
          },
          "email": {
            "type": "string",
            "nullable": true
          },
          "phoneNumber": {
            "type": "string",
            "nullable": true
          },
          "tableReservations": {
            "type": "array",
            "items": {
              "$ref": "#/components/schemas/TableResDTO"
            },
            "nullable": true
          }
        },
        "additionalProperties": false
      },
      "CustomerPromotions": {
        "type": "object",
        "properties": {
          "id": {
            "type": "integer",
            "format": "int32"
          },
          "customerId": {
            "type": "integer",
            "format": "int32"
          },
          "promotionId": {
            "type": "integer",
            "format": "int32"
          },
          "dateReceived": {
            "type": "string",
            "format": "date-time"
          },
          "dateRedeemed": {
            "type": "string",
            "format": "date-time"
          },
          "promoStatus": {
            "type": "string",
            "nullable": true
          },
          "customer": {
            "$ref": "#/components/schemas/Customers"
          },
          "promotion": {
            "$ref": "#/components/schemas/Promotions"
          }
        },
        "additionalProperties": false
      },
      "Customers": {
        "type": "object",
        "properties": {
          "customerID": {
            "type": "integer",
            "format": "int32"
          },
          "customerName": {
            "type": "string",
            "nullable": true
          },
          "email": {
            "type": "string",
            "nullable": true
          },
          "phoneNumber": {
            "type": "string",
            "nullable": true
          },
          "passwordHash": {
            "type": "string",
            "nullable": true
          },
          "address": {
            "type": "string",
            "nullable": true
          },
          "loyaltyPoints": {
            "type": "integer",
            "format": "int32",
            "nullable": true
          },
          "createdAt": {
            "type": "string",
            "format": "date-time"
          },
          "lastVisited": {
            "type": "string",
            "format": "date-time"
          },
          "isActive": {
            "type": "boolean"
          },
          "orders": {
            "type": "array",
            "items": {
              "$ref": "#/components/schemas/Orders"
            },
            "nullable": true
          },
          "tableReservations": {
            "type": "array",
            "items": {
              "$ref": "#/components/schemas/TableReservations"
            },
            "nullable": true
          },
          "customerPromotions": {
            "type": "array",
            "items": {
              "$ref": "#/components/schemas/CustomerPromotions"
            },
            "nullable": true
          }
        },
        "additionalProperties": false
      },
      "ItemVariants": {
        "type": "object",
        "properties": {
          "variantId": {
            "type": "integer",
            "format": "int32",
            "nullable": true
          },
          "itemId": {
            "type": "integer",
            "format": "int32"
          },
          "variantName": {
            "type": "string",
            "nullable": true
          },
          "additionalPrice": {
            "type": "number",
            "format": "double"
          },
          "isDefault": {
            "type": "boolean"
          },
          "item": {
            "$ref": "#/components/schemas/MenuItems"
          },
          "orderItems": {
            "type": "array",
            "items": {
              "$ref": "#/components/schemas/OrderItems"
            },
            "nullable": true
          }
        },
        "additionalProperties": false
      },
      "MenuCategories": {
        "type": "object",
        "properties": {
          "categoryID": {
            "type": "integer",
            "format": "int32"
          },
          "categoryName": {
            "type": "string",
            "nullable": true
          },
          "description": {
            "type": "string",
            "nullable": true
          },
          "displayOrder": {
            "type": "integer",
            "format": "int32"
          },
          "isActive": {
            "type": "boolean"
          },
          "items": {
            "type": "array",
            "items": {
              "$ref": "#/components/schemas/MenuItems"
            },
            "nullable": true
          }
        },
        "additionalProperties": false
      },
      "MenuItems": {
        "type": "object",
        "properties": {
          "itemId": {
            "type": "integer",
            "format": "int32"
          },
          "menuCategoryId": {
            "type": "integer",
            "format": "int32"
          },
          "itemName": {
            "type": "string",
            "nullable": true
          },
          "description": {
            "type": "string",
            "nullable": true
          },
          "basePrice": {
            "type": "number",
            "format": "double"
          },
          "isAvailable": {
            "type": "boolean"
          },
          "isFeatured": {
            "type": "boolean"
          },
          "imageUrl": {
            "type": "string",
            "nullable": true
          },
          "menuCategory": {
            "$ref": "#/components/schemas/MenuCategories"
          },
          "itemsVariant": {
            "type": "array",
            "items": {
              "$ref": "#/components/schemas/ItemVariants"
            },
            "nullable": true
          },
          "orders": {
            "type": "array",
            "items": {
              "$ref": "#/components/schemas/Orders"
            },
            "nullable": true
          },
          "promotions": {
            "type": "array",
            "items": {
              "$ref": "#/components/schemas/Promotions"
            },
            "nullable": true
          }
        },
        "additionalProperties": false
      },
      "Operation": {
        "type": "object",
        "properties": {
          "value": {
            "nullable": true
          },
          "path": {
            "type": "string",
            "nullable": true
          },
          "op": {
            "type": "string",
            "nullable": true
          },
          "from": {
            "type": "string",
            "nullable": true
          }
        },
        "additionalProperties": false
      },
      "OrderDto": {
        "type": "object",
        "properties": {
          "orderId": {
            "type": "integer",
            "format": "int32"
          },
          "orderItems": {
            "type": "array",
            "items": {
              "type": "string"
            },
            "nullable": true
          },
          "orderStatus": {
            "type": "string",
            "nullable": true
          },
          "finalAmount": {
            "type": "number",
            "format": "double"
          }
        },
        "additionalProperties": false
      },
      "OrderItems": {
        "type": "object",
        "properties": {
          "orderItemId": {
            "type": "integer",
            "format": "int32"
          },
          "orderId": {
            "type": "integer",
            "format": "int32"
          },
          "itemId": {
            "type": "integer",
            "format": "int32"
          },
          "variantId": {
            "type": "integer",
            "format": "int32"
          },
          "quantity": {
            "type": "integer",
            "format": "int32"
          },
          "unitPrice": {
            "type": "number",
            "format": "double"
          },
          "specialRequests": {
            "type": "string",
            "nullable": true
          },
          "itemStatus": {
            "type": "string",
            "nullable": true
          },
          "item": {
            "$ref": "#/components/schemas/MenuItems"
          },
          "order": {
            "$ref": "#/components/schemas/Orders"
          },
          "variant": {
            "$ref": "#/components/schemas/ItemVariants"
          }
        },
        "additionalProperties": false
      },
      "Orders": {
        "type": "object",
        "properties": {
          "orderId": {
            "type": "integer",
            "format": "int32"
          },
          "customerId": {
            "type": "integer",
            "format": "int32"
          },
          "orderType": {
            "type": "string",
            "nullable": true
          },
          "orderDate": {
            "type": "string",
            "format": "date-time"
          },
          "totalAmount": {
            "type": "number",
            "format": "double"
          },
          "discountAmount": {
            "type": "number",
            "format": "double"
          },
          "taxAmount": {
            "type": "number",
            "format": "double"
          },
          "finalAmount": {
            "type": "number",
            "format": "double"
          },
          "paymentMethod": {
            "type": "string",
            "nullable": true
          },
          "paymentStatus": {
            "type": "string",
            "nullable": true
          },
          "orderStatus": {
            "type": "string",
            "nullable": true
          },
          "specialInstructions": {
            "type": "string",
            "nullable": true
          },
          "reservationId": {
            "type": "integer",
            "format": "int32",
            "nullable": true
          },
          "customer": {
            "$ref": "#/components/schemas/Customers"
          },
          "orderItems": {
            "type": "array",
            "items": {
              "$ref": "#/components/schemas/OrderItems"
            },
            "nullable": true
          },
          "tableReservation": {
            "$ref": "#/components/schemas/TableReservations"
          },
          "admin": {
            "type": "array",
            "items": {
              "$ref": "#/components/schemas/Admins"
            },
            "nullable": true
          }
        },
        "additionalProperties": false
      },
      "Promotions": {
        "type": "object",
        "properties": {
          "promoID": {
            "type": "string",
            "nullable": true
          },
          "adminID": {
            "type": "integer",
            "format": "int32"
          },
          "promoName": {
            "type": "string",
            "nullable": true
          },
          "promoDescription": {
            "type": "string",
            "nullable": true
          },
          "discountType": {
            "type": "string",
            "nullable": true
          },
          "discountValue": {
            "type": "number",
            "format": "double"
          },
          "startDate": {
            "type": "string",
            "format": "date-time"
          },
          "endDate": {
            "type": "string",
            "format": "date-time"
          },
          "minOrder": {
            "type": "number",
            "format": "double"
          },
          "applicableItemId": {
            "type": "integer",
            "format": "int32"
          },
          "promoStatus": {
            "type": "string",
            "nullable": true
          },
          "createdAt": {
            "type": "string",
            "format": "date-time"
          },
          "sentPromotions": {
            "type": "array",
            "items": {
              "$ref": "#/components/schemas/CustomerPromotions"
            },
            "nullable": true
          },
          "admins": {
            "type": "array",
            "items": {
              "$ref": "#/components/schemas/Admins"
            },
            "nullable": true
          },
          "menuItems": {
            "type": "array",
            "items": {
              "$ref": "#/components/schemas/MenuItems"
            },
            "nullable": true
          }
        },
        "additionalProperties": false
      },
      "TableResDTO": {
        "type": "object",
        "properties": {
          "reservationId": {
            "type": "integer",
            "format": "int32"
          },
          "customerId": {
            "type": "integer",
            "format": "int32"
          },
          "tableId": {
            "type": "integer",
            "format": "int32"
          },
          "reservationDate": {
            "type": "string",
            "format": "date"
          },
          "start_time": {
            "type": "string",
            "format": "time"
          },
          "end_time": {
            "type": "string",
            "format": "time"
          },
          "seatsNumbers": {
            "type": "integer",
            "format": "int32"
          },
          "specialRequests": {
            "type": "string",
            "nullable": true
          },
          "reservationStatus": {
            "type": "string",
            "nullable": true
          }
        },
        "additionalProperties": false
      },
      "TableReservations": {
        "type": "object",
        "properties": {
          "reservationId": {
            "type": "integer",
            "format": "int32"
          },
          "customerId": {
            "type": "integer",
            "format": "int32"
          },
          "tableId": {
            "type": "integer",
            "format": "int32"
          },
          "reservationDate": {
            "type": "string",
            "format": "date"
          },
          "start_time": {
            "type": "string",
            "format": "time"
          },
          "end_time": {
            "type": "string",
            "format": "time"
          },
          "seatsNumbers": {
            "type": "integer",
            "format": "int32"
          },
          "specialRequests": {
            "type": "string",
            "nullable": true
          },
          "reservationStatus": {
            "type": "string",
            "nullable": true
          },
          "createdAt": {
            "type": "string",
            "format": "date-time"
          },
          "customers": {
            "$ref": "#/components/schemas/Customers"
          },
          "orders": {
            "type": "array",
            "items": {
              "$ref": "#/components/schemas/Orders"
            },
            "nullable": true
          },
          "tables": {
            "$ref": "#/components/schemas/Tables"
          }
        },
        "additionalProperties": false
      },
      "Tables": {
        "type": "object",
        "properties": {
          "tableId": {
            "type": "integer",
            "format": "int32"
          },
          "tableAvailability": {
            "type": "boolean"
          },
          "tableCapacity": {
            "type": "integer",
            "format": "int32"
          },
          "tableLocation": {
            "type": "string",
            "nullable": true
          },
          "tableReservations": {
            "type": "array",
            "items": {
              "$ref": "#/components/schemas/TableReservations"
            },
            "nullable": true
          }
        },
        "additionalProperties": false
      }
    }
  }
}